bardclient.py
bardclient-1.1.dist-info/LICENSE
bardclient-1.1.dist-info/METADATA
bardclient-1.1.dist-info/WHEEL
bardclient-1.1.dist-info/top_level.txt
bardclient-1.1.dist-info/RECORD
