Metadata-Version: 2.1
Name: bardclient
Version: 1.1
Summary: A simple reverse engineering of google's bard implements by python3
Home-page: https://github.com/ydg119/bardclient
Author: yangdage
Author-email: 314474977@qq.com
License: MIT License
Classifier: License :: OSI Approved :: MIT License
Classifier: Intended Audience :: Developers
Classifier: Topic :: Software Development :: Libraries :: Python Modules
Classifier: Programming Language :: Python :: 3.8
Classifier: Programming Language :: Python :: 3.9
Classifier: Programming Language :: Python :: 3.10
Classifier: Programming Language :: Python :: 3.11
License-File: LICENSE
